premath/__init__.py
premath/linearr.py
premath-0.2.dist-info/LICENSE
premath-0.2.dist-info/METADATA
premath-0.2.dist-info/WHEEL
premath-0.2.dist-info/top_level.txt
premath-0.2.dist-info/RECORD
